fla/__init__.py
fla/utils.py
fla/layers/__init__.py
fla/layers/abc.py
fla/layers/attn.py
fla/layers/based.py
fla/layers/bitattn.py
fla/layers/comba.py
fla/layers/delta_net.py
fla/layers/forgetting_attn.py
fla/layers/gated_deltanet.py
fla/layers/gated_deltaproduct.py
fla/layers/gla.py
fla/layers/gsa.py
fla/layers/hgrn.py
fla/layers/hgrn2.py
fla/layers/lightnet.py
fla/layers/linear_attn.py
fla/layers/mamba.py
fla/layers/mamba2.py
fla/layers/mesa_net.py
fla/layers/mla.py
fla/layers/mom.py
fla/layers/multiscale_retention.py
fla/layers/nsa.py
fla/layers/path_attn.py
fla/layers/rebased.py
fla/layers/rodimus.py
fla/layers/rwkv6.py
fla/layers/rwkv7.py
fla/layers/simple_gla.py
fla/layers/utils.py
fla/models/__init__.py
fla/models/utils.py
fla/models/abc/__init__.py
fla/models/abc/configuration_abc.py
fla/models/abc/modeling_abc.py
fla/models/bitnet/__init__.py
fla/models/bitnet/configuration_bitnet.py
fla/models/bitnet/modeling_bitnet.py
fla/models/comba/__init__.py
fla/models/comba/configuration_comba.py
fla/models/comba/modeling_comba.py
fla/models/delta_net/__init__.py
fla/models/delta_net/configuration_delta_net.py
fla/models/delta_net/modeling_delta_net.py
fla/models/forgetting_transformer/__init__.py
fla/models/forgetting_transformer/configuration_forgetting_transformer.py
fla/models/forgetting_transformer/modeling_forgetting_transformer.py
fla/models/gated_deltanet/__init__.py
fla/models/gated_deltanet/configuration_gated_deltanet.py
fla/models/gated_deltanet/modeling_gated_deltanet.py
fla/models/gated_deltaproduct/__init__.py
fla/models/gated_deltaproduct/configuration_gated_deltaproduct.py
fla/models/gated_deltaproduct/modeling_gated_deltaproduct.py
fla/models/gla/__init__.py
fla/models/gla/configuration_gla.py
fla/models/gla/modeling_gla.py
fla/models/gsa/__init__.py
fla/models/gsa/configuration_gsa.py
fla/models/gsa/modeling_gsa.py
fla/models/hgrn/__init__.py
fla/models/hgrn/configuration_hgrn.py
fla/models/hgrn/modeling_hgrn.py
fla/models/hgrn2/__init__.py
rwkv_fla-0.7.202508221413.dist-info/licenses/LICENSE
rwkv_fla-0.7.202508221413.dist-info/METADATA
rwkv_fla-0.7.202508221413.dist-info/WHEEL
rwkv_fla-0.7.202508221413.dist-info/dependency_links.txt
rwkv_fla-0.7.202508221413.dist-info/top_level.txt
rwkv_fla-0.7.202508221413.dist-info/RECORD
