Metadata-Version: 2.4
Name: rwkv-fla
Version: 0.7.202508221413
Summary: Fast Triton-based implementations for RWKV
Home-page: https://github.com/TorchRWKV/flash-linear-attention
Author: Zhiyuan Li, Songlin Yang, Yu Zhang
Author-email: Zhiyuan Li <uniartisan2017@gmail.com>, Songlin Yang <yangsl66@mit.edu>, Yu Zhang <yzhang.cs@outlook.com>
License: MIT License
Project-URL: Homepage, https://github.com/fla-org/flash-linear-attention
Classifier: Programming Language :: Python :: 3
Classifier: License :: OSI Approved :: MIT License
Classifier: Operating System :: OS Independent
Classifier: Topic :: Scientific/Engineering :: Artificial Intelligence
Requires-Python: >=3.10
License-File: LICENSE
Requires-Dist: transformers>=4.45.0
Requires-Dist: datasets>=3.3.0
Requires-Dist: einops
Requires-Dist: pytest
Provides-Extra: conv1d
Requires-Dist: causal-conv1d>=1.4.0; extra == "conv1d"
Provides-Extra: benchmark
Requires-Dist: matplotlib; extra == "benchmark"
Dynamic: author
Dynamic: home-page
Dynamic: license-file
Dynamic: requires-python
